jax_dataloader/__init__.py
jax_dataloader/jax_dataloader.py
jax_dataloader/utils.py
jax_dataloader/data/__init__.py
jax_dataloader/exceptions/__init__.py
jax_dataloader/memory/Cargo.toml
jax_dataloader/memory/__init__.py
jax_dataloader/memory/rust_loader.py
jax_dataloader/memory/src/lib.rs
jax_dataloader/progress/__init__.py
jax_dataloader/transform/__init__.py
jax_dataloader/utils/__init__.py
jax_dataloaders-0.1.10.data/data/examples/README.md
jax_dataloaders-0.1.10.data/data/examples/requirements.txt
jax_dataloaders-0.1.10.dist-info/LICENSE
jax_dataloaders-0.1.10.dist-info/METADATA
jax_dataloaders-0.1.10.dist-info/WHEEL
jax_dataloaders-0.1.10.dist-info/top_level.txt
jax_dataloaders-0.1.10.dist-info/RECORD
