Metadata-Version: 2.1
Name: jax-dataloaders
Version: 0.1.10
Summary: A high-performance data loading library for JAX
Home-page: https://github.com/carrycooldude/JAX-Dataloader
Author: Kartikey Rawat
Author-email: rawatkari554@gmail.com
Classifier: Development Status :: 3 - Alpha
Classifier: Intended Audience :: Developers
Classifier: License :: OSI Approved :: MIT License
Classifier: Operating System :: OS Independent
Classifier: Programming Language :: Python :: 3
Classifier: Programming Language :: Python :: 3.8
Classifier: Programming Language :: Python :: 3.9
Classifier: Programming Language :: Python :: 3.10
Classifier: Programming Language :: Python :: 3.11
Classifier: Topic :: Software Development :: Libraries :: Python Modules
Requires-Python: >=3.8
License-File: LICENSE
Requires-Dist: jax>=0.4.13
Requires-Dist: jaxlib>=0.4.13
Requires-Dist: numpy>=1.24.0
Requires-Dist: pandas>=2.0.0
Requires-Dist: pillow>=10.0.0
Requires-Dist: tqdm>=4.65.0
Requires-Dist: psutil>=5.9.0
Requires-Dist: typing-extensions>=4.5.0
Provides-Extra: all
Requires-Dist: pandas>=2.0.0; extra == "all"
Requires-Dist: pillow>=10.0.0; extra == "all"
Provides-Extra: csv
Requires-Dist: pandas>=2.0.0; extra == "csv"
Provides-Extra: dev
Requires-Dist: pytest>=7.0.0; extra == "dev"
Requires-Dist: pytest-cov>=4.0.0; extra == "dev"
Requires-Dist: black>=23.0.0; extra == "dev"
Requires-Dist: isort>=5.0.0; extra == "dev"
Requires-Dist: flake8>=6.0.0; extra == "dev"
Requires-Dist: mypy>=1.0.0; extra == "dev"
Requires-Dist: sphinx>=7.0.0; extra == "dev"
Requires-Dist: sphinx-rtd-theme>=1.0.0; extra == "dev"
Requires-Dist: sphinx-autodoc-typehints>=1.0.0; extra == "dev"
Provides-Extra: image
Requires-Dist: pillow>=10.0.0; extra == "image"
Provides-Extra: json
Requires-Dist: pandas>=2.0.0; extra == "json"
